test_tracer/__init__.py
test_tracer/main.py
test_tracer/test_case.py
test_tracer/trace_requirements.py
test_tracer/track_soup.py
test_tracer-0.1.0.dist-info/WHEEL
test_tracer-0.1.0.dist-info/entry_points.txt
test_tracer-0.1.0.dist-info/METADATA
test_tracer-0.1.0.dist-info/RECORD
