Metadata-Version: 2.3
Name: test-tracer
Version: 0.1.0
Summary: Test tracer tool for Dxcover
Author: JamesWooster
Author-email: JamesWooster <james.wooster@dxcover.com>
Requires-Dist: black>=25.9.0
Requires-Dist: coverage>=7.11.0
Requires-Dist: mypy>=1.18.2
Requires-Dist: openpyxl>=3.1.5
Requires-Dist: pytest>=8.4.2
Requires-Dist: black>=25.9.0 ; extra == 'dev'
Requires-Python: >=3.11
Project-URL: Homepage, https://https://github.com/Dxcover/test_tracer
Project-URL: Issues, https://github.com/Dxcover/test_tracer/issues
Provides-Extra: dev
